Workbook

Sheet Read_Me
B3: Project Overview
B4: This workbook is a simplified actuarial pricing model developed to calculate the premium for an individual term life insurance policy. The model applies actuarial pricing principles using mortality assumptions, discounting techniques, expense loading, profit loading, and projected cash flows to estimate both net and gross premiums.
B10: Objective
B11: The objective of this project is to: • Price a term life insurance product using actuarial techniques. • Demonstrate the calculation of Expected Present Value (EPV) of benefits and premiums. • Project insurer cash flows over the policy term. • Estimate gross premium by incorporating expenses, investment income, and profit loading. • Present pricing results through a structured Excel model and dashboard.
B19: Workbook Structure
B20: Worksheet | D20: Description
B21: Inputs | D21: Policy details and pricing assumptions
B22: Mortality Table | D22: Mortality rates and life table calculations
B23: Calculations | D23: Survival probabilities, death probabilities and EPV calculations
B24: Premium Calculations | D24: Premium present value factors and annuity calculations
B25: Premium | D25: Net and Gross Premium calculations
B26: Cashflow | D26: Annual premium inflows, benefits, expenses, investment income and net cash flows
B27: Checks | D27: Model validation and consistency checks
B28: Dashboard | D28: Summary of pricing results and charts

Sheet Inputs
C4: Field | D4: Input Value
C5: Policy Number | D5: POL0001
C6: Customer Name | D6: Amit Sharma
C7: Age | D7: 40
C8: Gender | D8: Male
C9: Policy Term (Years) | D9: 30
C10: Premium Term(Years) | D10: 20
C11: Sum Assured | D11: 100000
C12: Interest Rate | D12: 0.05
C13: Initial Expenses | D13: 0.3
C14: Renewal Expenses | D14: 0.06
C15: Initial Commission | D15: 0.6
C16: Renewal Commission | D16: 0.05
C17: Profit Loading | D17: 0
C18: Premium Frequency | D18: Annual
C19: Product Type | D19: Term
C20: Issue Date | D20: =TODAY() -> 46234

Sheet Mortality_Table
C2: MORTALITY TABLE : AM 92
C3: Age | D3: qx | E3: px | F3: lx | G3: dx | H3: Death | I3: Aqx
C4: 18 | D4: 0.000594 | E4: =1-D4 -> 0.999406 | F4: =1000 -> 1000 | G4: =F4*D4 -> 0.594 | H4: =MortalityTable[[#This Row],[lx]]-F5 -> 0.587 | I4: =MortalityTable[[#This Row],[Death]]/$F$4 -> 0.000587
C5: 19 | D5: 0.000587 | E5: =1-D5 -> 0.999413 | F5: =F4*E5 -> 999.413 | G5: =F5*D5 -> 0.58665543 | H5: =MortalityTable[[#This Row],[lx]]-F6 -> 0.58165837 | I5: =MortalityTable[[#This Row],[Death]]/$F$4 -> 0.00058165837
C6: 20 | D6: 0.000582 | E6: =1-D6 -> 0.999418 | F6: =F5*E6 -> 998.83134 | G6: =F6*D6 -> 0.58131984 | H6: =MortalityTable[[#This Row],[lx]]-F7 -> 0.57632568 | I6: =MortalityTable[[#This Row],[Death]]/$F$4 -> 0.00057632568
C7: 21 | D7: 0.000577 | E7: =1-D7 -> 0.999423 | F7: =F6*E7 -> 998.25502 | G7: =F7*D7 -> 0.57599314 | H7: =MortalityTable[[#This Row],[lx]]-F8 -> 0.57100187 | I7: =MortalityTable[[#This Row],[Death]]/$F$4 -> 0.00057100187
C8: 22 | D8: 0.000572 | E8: =1-D8 -> 0.999428 | F8: =F7*E8 -> 997.68401 | G8: =F8*D8 -> 0.57067526 | H8: =MortalityTable[[#This Row],[lx]]-F9 -> 0.5676822 | I8: =MortalityTable[[#This Row],[Death]]/$F$4 -> 0.0005676822
C9: 23 | D9: 0.000569 | E9: =1-D9 -> 0.999431 | F9: =F8*E9 -> 997.11633 | G9: =F9*D9 -> 0.56735919 | H9: =MortalityTable[[#This Row],[lx]]-F10 -> 0.56536496 | I9: =MortalityTable[[#This Row],[Death]]/$F$4 -> 0.00056536496
C10: 24 | D10: 0.000567 | E10: =1-D10 -> 0.999433 | F10: =F9*E10 -> 996.55097 | G10: =F10*D10 -> 0.5650444 | H10: =MortalityTable[[#This Row],[lx]]-F11 -> 0.56404785 | I10: =MortalityTable[[#This Row],[Death]]/$F$4 -> 0.00056404785
C11: 25 | D11: 0.000566 | E11: =1-D11 -> 0.999434 | F11: =F10*E11 -> 995.98692 | G11: =F11*D11 -> 0.5637286 | H11: =MortalityTable[[#This Row],[lx]]-F12 -> 0.56472458 | I11: =MortalityTable[[#This Row],[Death]]/$F$4 -> 0.00056472458
C12: 26 | D12: 0.000567 | E12: =1-D12 -> 0.999433 | F12: =F11*E12 -> 995.42219 | G12: =F12*D12 -> 0.56440438 | H12: =MortalityTable[[#This Row],[lx]]-F13 -> 0.56739065 | I12: =MortalityTable[[#This Row],[Death]]/$F$4 -> 0.00056739065
C13: 27 | D13: 0.00057 | E13: =1-D13 -> 0.99943 | F13: =F12*E13 -> 994.8548 | G13: =F13*D13 -> 0.56706724 | H13: =MortalityTable[[#This Row],[lx]]-F14 -> 0.57104666 | I13: =MortalityTable[[#This Row],[Death]]/$F$4 -> 0.00057104666
C14: 28 | D14: 0.000574 | E14: =1-D14 -> 0.999426 | F14: =F13*E14 -> 994.28376 | G14: =F14*D14 -> 0.57071888 | H14: =MortalityTable[[#This Row],[lx]]-F15 -> 0.57668458 | I14: =MortalityTable[[#This Row],[Death]]/$F$4 -> 0.00057668458
C15: 29 | D15: 0.00058 | E15: =1-D15 -> 0.99942 | F15: =F14*E15 -> 993.70707 | G15: =F15*D15 -> 0.5763501 | H15: =MortalityTable[[#This Row],[lx]]-F16 -> 0.58628717 | I15: =MortalityTable[[#This Row],[Death]]/$F$4 -> 0.00058628717
C16: 30 | D16: 0.00059 | E16: =1-D16 -> 0.99941 | F16: =F15*E16 -> 993.12079 | G16: =F16*D16 -> 0.58594126 | H16: =MortalityTable[[#This Row],[lx]]-F17 -> 0.59785871 | I16: =MortalityTable[[#This Row],[Death]]/$F$4 -> 0.00059785871
... C86: 100 | D86: 0.355505 | E86: =1-D86 -> 0.644495 | F86: =F85*E86 -> 6.1847115 | G86: =F86*D86 -> 2.1986959 | H86: =MortalityTable[[#This Row],[lx]]-F87 -> 6.1847115 | I86: =MortalityTable[[#This Row],[Death]]/$F$4 -> 0.0061847115

Sheet Calculations
B3: POLICY YEAR | C3: AGE | D3: qx | E3: px | F3: Probability of Death | G3: Discount Factor | H3: Benefits | I3: EPV of Benefits | J3: Cumulative EPV
B4: 1 | C4: =Inputs!$D$7+B4-1 -> 40 | D4: =IF(Inputs!$D$9>=Calculations!B4,INDEX(MortalityTable[qx],MATCH(C4,MortalityTable[Age]),0),0) -> 0.000937 | E4: =IF(Inputs!$D$9>=Calculations!B4,1-D4,0) -> 0.999063 | F4: =IF(Inputs!$D$9>=Calculations!B4,1*D4,0) -> 0.000937 | G4: =IF(Inputs!$D$9>=Calculations!B4,1/((1+Inputs!$D$12)^B4),0) -> 0.95238095 | H4: =IF(Inputs!$D$9>=Calculations!B4,Inputs!$D$11*Table2[[#This Row],[Probability of Death]],0) -> 93.7 | I4: =IF(Inputs!$D$9>=Calculations!B4,F4*Inputs!$D$11*G4,0) -> 89.238095 | J4: =IF(Inputs!$D$9>=Calculations!B4,SUM($I$4),0) -> 89.238095
B5: 2 | C5: =Inputs!$D$7+B5-1 -> 41 | D5: =IF(Inputs!$D$9>=Calculations!B5,INDEX(MortalityTable[qx],MATCH(C5,MortalityTable[Age]),0),0) -> 0.001014 | E5: =IF(Inputs!$D$9>=Calculations!B5,E4-(E4*D5),0) -> 0.99804995 | F5: =IF(Inputs!$D$9>=Calculations!B5,E4*D5,0) -> 0.0010130499 | G5: =IF(Inputs!$D$9>=Calculations!B5,1/((1+Inputs!$D$12)^B5),0) -> 0.90702948 | H5: =IF(Inputs!$D$9>=Calculations!B5,Inputs!$D$11*Table2[[#This Row],[Probability of Death]],0) -> 101.30499 | I5: =IF(Inputs!$D$9>=Calculations!B5,F5*Inputs!$D$11*G5,0) -> 91.886611 | J5: =IF(Inputs!$D$9>=Calculations!B5,SUM($I$4:I5),0) -> 181.12471
B6: 3 | C6: =Inputs!$D$7+B6-1 -> 42 | D6: =IF(Inputs!$D$9>=Calculations!B6,INDEX(MortalityTable[qx],MATCH(C6,MortalityTable[Age]),0),0) -> 0.001104 | E6: =IF(Inputs!$D$9>=Calculations!B6,E5-(E5*D6),0) -> 0.9969481 | F6: =IF(Inputs!$D$9>=Calculations!B6,E5*D6,0) -> 0.0011018471 | G6: =IF(Inputs!$D$9>=Calculations!B6,1/((1+Inputs!$D$12)^B6),0) -> 0.8638376 | H6: =IF(Inputs!$D$9>=Calculations!B6,Inputs!$D$11*Table2[[#This Row],[Probability of Death]],0) -> 110.18471 | I6: =IF(Inputs!$D$9>=Calculations!B6,F6*Inputs!$D$11*G6,0) -> 95.181699 | J6: =IF(Inputs!$D$9>=Calculations!B6,SUM($I$4:I6),0) -> 276.30641
B7: 4 | C7: =Inputs!$D$7+B7-1 -> 43 | D7: =IF(Inputs!$D$9>=Calculations!B7,INDEX(MortalityTable[qx],MATCH(C7,MortalityTable[Age]),0),0) -> 0.001208 | E7: =IF(Inputs!$D$9>=Calculations!B7,E6-(E6*D7),0) -> 0.99574379 | F7: =IF(Inputs!$D$9>=Calculations!B7,E6*D7,0) -> 0.0012043133 | G7: =IF(Inputs!$D$9>=Calculations!B7,1/((1+Inputs!$D$12)^B7),0) -> 0.82270247 | H7: =IF(Inputs!$D$9>=Calculations!B7,Inputs!$D$11*Table2[[#This Row],[Probability of Death]],0) -> 120.43133 | I7: =IF(Inputs!$D$9>=Calculations!B7,F7*Inputs!$D$11*G7,0) -> 99.079154 | J7: =IF(Inputs!$D$9>=Calculations!B7,SUM($I$4:I7),0) -> 375.38556
B8: 5 | C8: =Inputs!$D$7+B8-1 -> 44 | D8: =IF(Inputs!$D$9>=Calculations!B8,INDEX(MortalityTable[qx],MATCH(C8,MortalityTable[Age]),0),0) -> 0.001327 | E8: =IF(Inputs!$D$9>=Calculations!B8,E7-(E7*D8),0) -> 0.99442244 | F8: =IF(Inputs!$D$9>=Calculations!B8,E7*D8,0) -> 0.001321352 | G8: =IF(Inputs!$D$9>=Calculations!B8,1/((1+Inputs!$D$12)^B8),0) -> 0.78352617 | H8: =IF(Inputs!$D$9>=Calculations!B8,Inputs!$D$11*Table2[[#This Row],[Probability of Death]],0) -> 132.1352 | I8: =IF(Inputs!$D$9>=Calculations!B8,F8*Inputs!$D$11*G8,0) -> 103.53139 | J8: =IF(Inputs!$D$9>=Calculations!B8,SUM($I$4:I8),0) -> 478.91695
B9: 6 | C9: =Inputs!$D$7+B9-1 -> 45 | D9: =IF(Inputs!$D$9>=Calculations!B9,INDEX(MortalityTable[qx],MATCH(C9,MortalityTable[Age]),0),0) -> 0.001465 | E9: =IF(Inputs!$D$9>=Calculations!B9,E8-(E8*D9),0) -> 0.99296561 | F9: =IF(Inputs!$D$9>=Calculations!B9,E8*D9,0) -> 0.0014568289 | G9: =IF(Inputs!$D$9>=Calculations!B9,1/((1+Inputs!$D$12)^B9),0) -> 0.7462154 | H9: =IF(Inputs!$D$9>=Calculations!B9,Inputs!$D$11*Table2[[#This Row],[Probability of Death]],0) -> 145.68289 | I9: =IF(Inputs!$D$9>=Calculations!B9,F9*Inputs!$D$11*G9,0) -> 108.71081 | J9: =IF(Inputs!$D$9>=Calculations!B9,SUM($I$4:I9),0) -> 587.62776
B10: 7 | C10: =Inputs!$D$7+B10-1 -> 46 | D10: =IF(Inputs!$D$9>=Calculations!B10,INDEX(MortalityTable[qx],MATCH(C10,MortalityTable[Age]),0),0) -> 0.001622 | E10: =IF(Inputs!$D$9>=Calculations!B10,E9-(E9*D10),0) -> 0.99135502 | F10: =IF(Inputs!$D$9>=Calculations!B10,E9*D10,0) -> 0.0016105902 | G10: =IF(Inputs!$D$9>=Calculations!B10,1/((1+Inputs!$D$12)^B10),0) -> 0.71068133 | H10: =IF(Inputs!$D$9>=Calculations!B10,Inputs!$D$11*Table2[[#This Row],[Probability of Death]],0) -> 161.05902 | I10: =IF(Inputs!$D$9>=Calculations!B10,F10*Inputs!$D$11*G10,0) -> 114.46164 | J10: =IF(Inputs!$D$9>=Calculations!B10,SUM($I$4:I10),0) -> 702.0894
B11: 8 | C11: =Inputs!$D$7+B11-1 -> 47 | D11: =IF(Inputs!$D$9>=Calculations!B11,INDEX(MortalityTable[qx],MATCH(C11,MortalityTable[Age]),0),0) -> 0.001802 | E11: =IF(Inputs!$D$9>=Calculations!B11,E10-(E10*D11),0) -> 0.9895686 | F11: =IF(Inputs!$D$9>=Calculations!B11,E10*D11,0) -> 0.0017864217 | G11: =IF(Inputs!$D$9>=Calculations!B11,1/((1+Inputs!$D$12)^B11),0) -> 0.67683936 | H11: =IF(Inputs!$D$9>=Calculations!B11,Inputs!$D$11*Table2[[#This Row],[Probability of Death]],0) -> 178.64217 | I11: =IF(Inputs!$D$9>=Calculations!B11,F11*Inputs!$D$11*G11,0) -> 120.91206 | J11: =IF(Inputs!$D$9>=Calculations!B11,SUM($I$4:I11),0) -> 823.00145
B12: 9 | C12: =Inputs!$D$7+B12-1 -> 48 | D12: =IF(Inputs!$D$9>=Calculations!B12,INDEX(MortalityTable[qx],MATCH(C12,MortalityTable[Age]),0),0) -> 0.002008 | E12: =IF(Inputs!$D$9>=Calculations!B12,E11-(E11*D12),0) -> 0.98758154 | F12: =IF(Inputs!$D$9>=Calculations!B12,E11*D12,0) -> 0.0019870537 | G12: =IF(Inputs!$D$9>=Calculations!B12,1/((1+Inputs!$D$12)^B12),0) -> 0.64460892 | H12: =IF(Inputs!$D$9>=Calculations!B12,Inputs!$D$11*Table2[[#This Row],[Probability of Death]],0) -> 198.70537 | I12: =IF(Inputs!$D$9>=Calculations!B12,F12*Inputs!$D$11*G12,0) -> 128.08726 | J12: =IF(Inputs!$D$9>=Calculations!B12,SUM($I$4:I12),0) -> 951.08871
B13: 10 | C13: =Inputs!$D$7+B13-1 -> 49 | D13: =IF(Inputs!$D$9>=Calculations!B13,INDEX(MortalityTable[qx],MATCH(C13,MortalityTable[Age]),0),0) -> 0.002241 | E13: =IF(Inputs!$D$9>=Calculations!B13,E12-(E12*D13),0) -> 0.98536837 | F13: =IF(Inputs!$D$9>=Calculations!B13,E12*D13,0) -> 0.0022131702 | G13: =IF(Inputs!$D$9>=Calculations!B13,1/((1+Inputs!$D$12)^B13),0) -> 0.61391325 | H13: =IF(Inputs!$D$9>=Calculations!B13,Inputs!$D$11*Table2[[#This Row],[Probability of Death]],0) -> 221.31702 | I13: =IF(Inputs!$D$9>=Calculations!B13,F13*Inputs!$D$11*G13,0) -> 135.86945 | J13: =IF(Inputs!$D$9>=Calculations!B13,SUM($I$4:I13),0) -> 1086.9582
B14: 11 | C14: =Inputs!$D$7+B14-1 -> 50 | D14: =IF(Inputs!$D$9>=Calculations!B14,INDEX(MortalityTable[qx],MATCH(C14,MortalityTable[Age]),0),0) -> 0.002508 | E14: =IF(Inputs!$D$9>=Calculations!B14,E13-(E13*D14),0) -> 0.98289707 | F14: =IF(Inputs!$D$9>=Calculations!B14,E13*D14,0) -> 0.0024713039 | G14: =IF(Inputs!$D$9>=Calculations!B14,1/((1+Inputs!$D$12)^B14),0) -> 0.58467929 | H14: =IF(Inputs!$D$9>=Calculations!B14,Inputs!$D$11*Table2[[#This Row],[Probability of Death]],0) -> 247.13039 | I14: =IF(Inputs!$D$9>=Calculations!B14,F14*Inputs!$D$11*G14,0) -> 144.49202 | J14: =IF(Inputs!$D$9>=Calculations!B14,SUM($I$4:I14),0) -> 1231.4502
B15: 12 | C15: =Inputs!$D$7+B15-1 -> 51 | D15: =IF(Inputs!$D$9>=Calculations!B15,INDEX(MortalityTable[qx],MATCH(C15,MortalityTable[Age]),0),0) -> 0.002809 | E15: =IF(Inputs!$D$9>=Calculations!B15,E14-(E14*D15),0) -> 0.98013611 | F15: =IF(Inputs!$D$9>=Calculations!B15,E14*D15,0) -> 0.0027609579 | G15: =IF(Inputs!$D$9>=Calculations!B15,1/((1+Inputs!$D$12)^B15),0) -> 0.55683742 | H15: =IF(Inputs!$D$9>=Calculations!B15,Inputs!$D$11*Table2[[#This Row],[Probability of Death]],0) -> 276.09579 | I15: =IF(Inputs!$D$9>=Calculations!B15,F15*Inputs!$D$11*G15,0) -> 153.74047 | J15: =IF(Inputs!$D$9>=Calculations!B15,SUM($I$4:I15),0) -> 1385.1906
B16: 13 | C16: =Inputs!$D$7+B16-1 -> 52 | D16: =IF(Inputs!$D$9>=Calculations!B16,INDEX(MortalityTable[qx],MATCH(C16,MortalityTable[Age]),0),0) -> 0.003152 | E16: =IF(Inputs!$D$9>=Calculations!B16,E15-(E15*D16),0) -> 0.97704672 | F16: =IF(Inputs!$D$9>=Calculations!B16,E15*D16,0) -> 0.003089389 | G16: =IF(Inputs!$D$9>=Calculations!B16,1/((1+Inputs!$D$12)^B16),0) -> 0.53032135 | H16: =IF(Inputs!$D$9>=Calculations!B16,Inputs!$D$11*Table2[[#This Row],[Probability of Death]],0) -> 308.9389 | I16: =IF(Inputs!$D$9>=Calculations!B16,F16*Inputs!$D$11*G16,0) -> 163.8369 | J16: =IF(Inputs!$D$9>=Calculations!B16,SUM($I$4:I16),0) -> 1549.0275
... B85: 82 | C85: =Inputs!$D$7+B85-1 -> 121 | D85: =IF(Inputs!$D$9>=Calculations!B85,INDEX(MortalityTable[qx],MATCH(C85,MortalityTable[Age]),0),0) -> 0 | E85: =IF(Inputs!$D$9>=Calculations!B85,E84-(E84*D85),0) -> 0 | F85: =IF(Inputs!$D$9>=Calculations!B85,E84*D85,0) -> 0 | G85: =IF(Inputs!$D$9>=Calculations!B85,1/((1+Inputs!$D$12)^B85),0) -> 0 | H85: =IF(Inputs!$D$9>=Calculations!B85,Inputs!$D$11*Table2[[#This Row],[Probability of Death]],0) -> 0 | I85: =IF(Inputs!$D$9>=Calculations!B85,F85*Inputs!$D$11*G85,0) -> 0 | J85: =IF(Inputs!$D$9>=Calculations!B85,SUM($I$4:I85),0) -> 0
B86: TOTAL | F86: =SUM(F4:F85) -> 0.18285101 | G86: =SUM(G4:G85) -> 15.372451 | H86: =SUM(H4:H85) -> 18285.101 | I86: =SUM(I4:I85) -> 6540.2965

Sheet Premium_Calculations
B3: Policy Year | C3: Age | D3: Survival Probability | E3: Discount Factor | F3: Premium PV Factor | G3: NET PREMIUM | H3: Initial Expenses | I3: Renewal Expenses | J3: Initial Commission | K3: Renewal Commission | L3: Profit Loading | M3: GROSS PREMIUM PV
B4: 1 | C4: =Inputs!D7 -> 40 | D4: =Table2[[#This Row],[px]] -> 0.999063 | E4: =IF(Inputs!$D$10>=Premium_Calculations!B4,1/((1+Inputs!$D$12)^(Premium_Calculations!B4-1)),0) -> 1 | F4: =E4 -> 1 | G4: =IF(Inputs!$D$10>=Premium_Calculations!B4,(Premium!$C$17/Premium!$C$18)*F4,0) -> 506.85539 | H4: =Premium!C28*Inputs!$D$13 -> 183.47106 | I4: 0 | J4: =Premium!$C$28*Inputs!$D$15 -> 366.94212 | K4: 0 | L4: =IF(Inputs!$D$10>=Premium_Calculations!B4,Premium!$C$28*Inputs!$D$17*F4,0) -> 0 | M4: =SUM(G4:L4) -> 1057.2686
B5: 2 | C5: =C4+1 -> 41 | D5: =Table2[[#This Row],[px]] -> 0.99804995 | E5: =IF(Inputs!$D$10>=Premium_Calculations!B5,1/((1+Inputs!$D$12)^(Premium_Calculations!B5-1)),0) -> 0.95238095 | F5: =IF(Inputs!$D$10>=Premium_Calculations!B5,D4*E5,0) -> 0.95148857 | G5: =IF(Inputs!$D$10>=Premium_Calculations!B5,(Premium!$C$17/Premium!$C$18)*F5,0) -> 482.26711 | H5: 0 | I5: =IF(Inputs!$D$10>=Premium_Calculations!B5,Premium!$C$28*Inputs!$D$14*F5,0) -> 34.914123 | J5: 0 | K5: =IF(Inputs!$D$10>=Premium_Calculations!B5,Premium!$C$28*Inputs!$D$16*F5,0) -> 29.095103 | L5: =IF(Inputs!$D$10>=Premium_Calculations!B5,Premium!$C$28*Inputs!$D$17*F5,0) -> 0 | M5: =SUM(G5:L5) -> 546.27633
B6: 3 | C6: =C5+1 -> 42 | D6: =Table2[[#This Row],[px]] -> 0.9969481 | E6: =IF(Inputs!$D$10>=Premium_Calculations!B6,1/((1+Inputs!$D$12)^(Premium_Calculations!B6-1)),0) -> 0.90702948 | F6: =IF(Inputs!$D$10>=Premium_Calculations!B6,D5*E6,0) -> 0.90526073 | G6: =IF(Inputs!$D$10>=Premium_Calculations!B6,(Premium!$C$17/Premium!$C$18)*F6,0) -> 458.83628 | H6: 0 | I6: =IF(Inputs!$D$10>=Premium_Calculations!B6,Premium!$C$28*Inputs!$D$14*F6,0) -> 33.217829 | J6: 0 | K6: =IF(Inputs!$D$10>=Premium_Calculations!B6,Premium!$C$28*Inputs!$D$16*F6,0) -> 27.681524 | L6: =IF(Inputs!$D$10>=Premium_Calculations!B6,Premium!$C$28*Inputs!$D$17*F6,0) -> 0 | M6: =SUM(G6:L6) -> 519.73563
B7: 4 | C7: =C6+1 -> 43 | D7: =Table2[[#This Row],[px]] -> 0.99574379 | E7: =IF(Inputs!$D$10>=Premium_Calculations!B7,1/((1+Inputs!$D$12)^(Premium_Calculations!B7-1)),0) -> 0.8638376 | F7: =IF(Inputs!$D$10>=Premium_Calculations!B7,D6*E7,0) -> 0.86120126 | G7: =IF(Inputs!$D$10>=Premium_Calculations!B7,(Premium!$C$17/Premium!$C$18)*F7,0) -> 436.5045 | H7: 0 | I7: =IF(Inputs!$D$10>=Premium_Calculations!B7,Premium!$C$28*Inputs!$D$14*F7,0) -> 31.601101 | J7: 0 | K7: =IF(Inputs!$D$10>=Premium_Calculations!B7,Premium!$C$28*Inputs!$D$16*F7,0) -> 26.334251 | L7: =IF(Inputs!$D$10>=Premium_Calculations!B7,Premium!$C$28*Inputs!$D$17*F7,0) -> 0 | M7: =SUM(G7:L7) -> 494.43985
B8: 5 | C8: =C7+1 -> 44 | D8: =Table2[[#This Row],[px]] -> 0.99442244 | E8: =IF(Inputs!$D$10>=Premium_Calculations!B8,1/((1+Inputs!$D$12)^(Premium_Calculations!B8-1)),0) -> 0.82270247 | F8: =IF(Inputs!$D$10>=Premium_Calculations!B8,D7*E8,0) -> 0.81920088 | G8: =IF(Inputs!$D$10>=Premium_Calculations!B8,(Premium!$C$17/Premium!$C$18)*F8,0) -> 415.21638 | H8: 0 | I8: =IF(Inputs!$D$10>=Premium_Calculations!B8,Premium!$C$28*Inputs!$D$14*F8,0) -> 30.05993 | J8: 0 | K8: =IF(Inputs!$D$10>=Premium_Calculations!B8,Premium!$C$28*Inputs!$D$16*F8,0) -> 25.049942 | L8: =IF(Inputs!$D$10>=Premium_Calculations!B8,Premium!$C$28*Inputs!$D$17*F8,0) -> 0 | M8: =SUM(G8:L8) -> 470.32625
B9: 6 | C9: =C8+1 -> 45 | D9: =Table2[[#This Row],[px]] -> 0.99296561 | E9: =IF(Inputs!$D$10>=Premium_Calculations!B9,1/((1+Inputs!$D$12)^(Premium_Calculations!B9-1)),0) -> 0.78352617 | F9: =IF(Inputs!$D$10>=Premium_Calculations!B9,D8*E9,0) -> 0.779156 | G9: =IF(Inputs!$D$10>=Premium_Calculations!B9,(Premium!$C$17/Premium!$C$18)*F9,0) -> 394.91942 | H9: 0 | I9: =IF(Inputs!$D$10>=Premium_Calculations!B9,Premium!$C$28*Inputs!$D$14*F9,0) -> 28.590515 | J9: 0 | K9: =IF(Inputs!$D$10>=Premium_Calculations!B9,Premium!$C$28*Inputs!$D$16*F9,0) -> 23.825429 | L9: =IF(Inputs!$D$10>=Premium_Calculations!B9,Premium!$C$28*Inputs!$D$17*F9,0) -> 0 | M9: =SUM(G9:L9) -> 447.33536
B10: 7 | C10: =C9+1 -> 46 | D10: =Table2[[#This Row],[px]] -> 0.99135502 | E10: =IF(Inputs!$D$10>=Premium_Calculations!B10,1/((1+Inputs!$D$12)^(Premium_Calculations!B10-1)),0) -> 0.7462154 | F10: =IF(Inputs!$D$10>=Premium_Calculations!B10,D9*E10,0) -> 0.74096623 | G10: =IF(Inputs!$D$10>=Premium_Calculations!B10,(Premium!$C$17/Premium!$C$18)*F10,0) -> 375.56272 | H10: 0 | I10: =IF(Inputs!$D$10>=Premium_Calculations!B10,Premium!$C$28*Inputs!$D$14*F10,0) -> 27.189172 | J10: 0 | K10: =IF(Inputs!$D$10>=Premium_Calculations!B10,Premium!$C$28*Inputs!$D$16*F10,0) -> 22.657643 | L10: =IF(Inputs!$D$10>=Premium_Calculations!B10,Premium!$C$28*Inputs!$D$17*F10,0) -> 0 | M10: =SUM(G10:L10) -> 425.40954
B11: 8 | C11: =C10+1 -> 47 | D11: =Table2[[#This Row],[px]] -> 0.9895686 | E11: =IF(Inputs!$D$10>=Premium_Calculations!B11,1/((1+Inputs!$D$12)^(Premium_Calculations!B11-1)),0) -> 0.71068133 | F11: =IF(Inputs!$D$10>=Premium_Calculations!B11,D10*E11,0) -> 0.7045375 | G11: =IF(Inputs!$D$10>=Premium_Calculations!B11,(Premium!$C$17/Premium!$C$18)*F11,0) -> 357.09863 | H11: 0 | I11: =IF(Inputs!$D$10>=Premium_Calculations!B11,Premium!$C$28*Inputs!$D$14*F11,0) -> 25.852448 | J11: 0 | K11: =IF(Inputs!$D$10>=Premium_Calculations!B11,Premium!$C$28*Inputs!$D$16*F11,0) -> 21.543707 | L11: =IF(Inputs!$D$10>=Premium_Calculations!B11,Premium!$C$28*Inputs!$D$17*F11,0) -> 0 | M11: =SUM(G11:L11) -> 404.49478
B12: 9 | C12: =C11+1 -> 48 | D12: =Table2[[#This Row],[px]] -> 0.98758154 | E12: =IF(Inputs!$D$10>=Premium_Calculations!B12,1/((1+Inputs!$D$12)^(Premium_Calculations!B12-1)),0) -> 0.67683936 | F12: =IF(Inputs!$D$10>=Premium_Calculations!B12,D11*E12,0) -> 0.66977898 | G12: =IF(Inputs!$D$10>=Premium_Calculations!B12,(Premium!$C$17/Premium!$C$18)*F12,0) -> 339.48108 | H12: 0 | I12: =IF(Inputs!$D$10>=Premium_Calculations!B12,Premium!$C$28*Inputs!$D$14*F12,0) -> 24.577012 | J12: 0 | K12: =IF(Inputs!$D$10>=Premium_Calculations!B12,Premium!$C$28*Inputs!$D$16*F12,0) -> 20.480843 | L12: =IF(Inputs!$D$10>=Premium_Calculations!B12,Premium!$C$28*Inputs!$D$17*F12,0) -> 0 | M12: =SUM(G12:L12) -> 384.53894
B13: 10 | C13: =C12+1 -> 49 | D13: =Table2[[#This Row],[px]] -> 0.98536837 | E13: =IF(Inputs!$D$10>=Premium_Calculations!B13,1/((1+Inputs!$D$12)^(Premium_Calculations!B13-1)),0) -> 0.64460892 | F13: =IF(Inputs!$D$10>=Premium_Calculations!B13,D12*E13,0) -> 0.63660387 | G13: =IF(Inputs!$D$10>=Premium_Calculations!B13,(Premium!$C$17/Premium!$C$18)*F13,0) -> 322.6661 | H13: 0 | I13: =IF(Inputs!$D$10>=Premium_Calculations!B13,Premium!$C$28*Inputs!$D$14*F13,0) -> 23.359677 | J13: 0 | K13: =IF(Inputs!$D$10>=Premium_Calculations!B13,Premium!$C$28*Inputs!$D$16*F13,0) -> 19.466398 | L13: =IF(Inputs!$D$10>=Premium_Calculations!B13,Premium!$C$28*Inputs!$D$17*F13,0) -> 0 | M13: =SUM(G13:L13) -> 365.49217
B14: 11 | C14: =C13+1 -> 50 | D14: =Table2[[#This Row],[px]] -> 0.98289707 | E14: =IF(Inputs!$D$10>=Premium_Calculations!B14,1/((1+Inputs!$D$12)^(Premium_Calculations!B14-1)),0) -> 0.61391325 | F14: =IF(Inputs!$D$10>=Premium_Calculations!B14,D13*E14,0) -> 0.6049307 | G14: =IF(Inputs!$D$10>=Premium_Calculations!B14,(Premium!$C$17/Premium!$C$18)*F14,0) -> 306.61239 | H14: 0 | I14: =IF(Inputs!$D$10>=Premium_Calculations!B14,Premium!$C$28*Inputs!$D$14*F14,0) -> 22.197455 | J14: 0 | K14: =IF(Inputs!$D$10>=Premium_Calculations!B14,Premium!$C$28*Inputs!$D$16*F14,0) -> 18.497879 | L14: =IF(Inputs!$D$10>=Premium_Calculations!B14,Premium!$C$28*Inputs!$D$17*F14,0) -> 0 | M14: =SUM(G14:L14) -> 347.30772
B15: 12 | C15: =C14+1 -> 51 | D15: =Table2[[#This Row],[px]] -> 0.98013611 | E15: =IF(Inputs!$D$10>=Premium_Calculations!B15,1/((1+Inputs!$D$12)^(Premium_Calculations!B15-1)),0) -> 0.58467929 | F15: =IF(Inputs!$D$10>=Premium_Calculations!B15,D14*E15,0) -> 0.57467956 | G15: =IF(Inputs!$D$10>=Premium_Calculations!B15,(Premium!$C$17/Premium!$C$18)*F15,0) -> 291.27943 | H15: 0 | I15: =IF(Inputs!$D$10>=Premium_Calculations!B15,Premium!$C$28*Inputs!$D$14*F15,0) -> 21.087413 | J15: 0 | K15: =IF(Inputs!$D$10>=Premium_Calculations!B15,Premium!$C$28*Inputs!$D$16*F15,0) -> 17.572844 | L15: =IF(Inputs!$D$10>=Premium_Calculations!B15,Premium!$C$28*Inputs!$D$17*F15,0) -> 0 | M15: =SUM(G15:L15) -> 329.93969
B16: 13 | C16: =C15+1 -> 52 | D16: =Table2[[#This Row],[px]] -> 0.97704672 | E16: =IF(Inputs!$D$10>=Premium_Calculations!B16,1/((1+Inputs!$D$12)^(Premium_Calculations!B16-1)),0) -> 0.55683742 | F16: =IF(Inputs!$D$10>=Premium_Calculations!B16,D15*E16,0) -> 0.54577646 | G16: =IF(Inputs!$D$10>=Premium_Calculations!B16,(Premium!$C$17/Premium!$C$18)*F16,0) -> 276.62974 | H16: 0 | I16: =IF(Inputs!$D$10>=Premium_Calculations!B16,Premium!$C$28*Inputs!$D$14*F16,0) -> 20.026837 | J16: 0 | K16: =IF(Inputs!$D$10>=Premium_Calculations!B16,Premium!$C$28*Inputs!$D$16*F16,0) -> 16.689031 | L16: =IF(Inputs!$D$10>=Premium_Calculations!B16,Premium!$C$28*Inputs!$D$17*F16,0) -> 0 | M16: =SUM(G16:L16) -> 313.34561
... B85: 82 | C85: =C84+1 -> 121 | D85: =Table2[[#This Row],[px]] -> 0 | E85: =IF(Inputs!$D$10>=Premium_Calculations!B85,1/((1+Inputs!$D$12)^(Premium_Calculations!B85-1)),0) -> 0 | F85: =IF(Inputs!$D$10>=Premium_Calculations!B85,D84*E85,0) -> 0 | G85: =IF(Inputs!$D$10>=Premium_Calculations!B85,(Premium!$C$17/Premium!$C$18)*F85,0) -> 0 | H85: 0 | I85: =IF(Inputs!$D$10>=Premium_Calculations!B85,Premium!$C$28*Inputs!$D$14*F85,0) -> 0 | J85: 0 | K85: =IF(Inputs!$D$10>=Premium_Calculations!B85,Premium!$C$28*Inputs!$D$16*F85,0) -> 0 | L85: =IF(Inputs!$D$10>=Premium_Calculations!B85,Premium!$C$28*Inputs!$D$17*F85,0) -> 0 | M85: =SUM(G85:L85) -> 0
B86: TOTAL | E86: =SUM(E4:E85) -> 13.085321 | F86: =SUM(F4:F85) -> 12.903674 | G86: =SUM(G4:G85) -> 6540.2965 | H86: =SUM(H4:H85) -> 183.47106 | I86: =SUM(I4:I85) -> 436.79592 | J86: =SUM(J4:J85) -> 366.94212 | K86: =SUM(K4:K85) -> 363.9966 | L86: =SUM(L4:L85) -> 0 | M86: =SUM(M4:M85) -> 7891.5022

Sheet Cashflow
D2: Inflows | F2: Benefits Outgo | H2: Expenses | J2: Commissions
B3: Policy Year | C3: Age | D3: Premium Inflow | E3: Investment Income | F3: Death Benefit Outgo | G3: Surrender Outgo | H3: Initial Expenses | I3: Renewal Expenses | J3: Initial Commission | K3: Renewal Commission | L3: Profit | M3: Net Cash Flow | N3: Reserves
B4: 1 | C4: =Inputs!D7 -> 40 | D4: =IF(Inputs!$D$10>=Cashflow!B4,Premium!$C$28,0) -> 611.57019 | E4: =IF(Inputs!$D$9>=Cashflow!B4,(D4-I4-H4-J4-K4)*Inputs!$D$12,0) -> 3.057851 | F4: =Table2[[#This Row],[Benefits]] -> 93.7 | G4: 0 | H4: =Premium!C28*Inputs!$D$13 -> 183.47106 | I4: 0 | J4: =Premium!C28*Inputs!$D$15 -> 366.94212 | K4: 0 | L4: =D4*Premium!$C$23 -> 183.47106 | M4: =SUM(D4:E4)-SUM(F4:K4) -> -29.48513 | N4: =IF(Inputs!$D$9>=Cashflow!B4,SUM(D4:E4)-SUM(F4:K4),0) -> -29.48513
B5: 2 | C5: =C4+1 -> 41 | D5: =IF(Inputs!$D$10>=Cashflow!B5,Premium!$C$28*Premium_Calculations!D4,0) -> 610.99715 | E5: =IF(Inputs!$D$9>=Cashflow!B5,(D5-I5+N4-K5-H5-J5)*Inputs!$D$12,0) -> 25.715117 | F5: =Table2[[#This Row],[Benefits]] -> 101.30499 | G5: 0 | H5: 0 | I5: =IF(Inputs!$D$10>=Cashflow!B5,Premium!$C$28*Inputs!$D$14*Premium_Calculations!D4,0) -> 36.659829 | J5: 0 | K5: =IF(Inputs!$D$10>=Cashflow!B5,Premium!$C$28*Inputs!$D$16*Premium_Calculations!D4,0) -> 30.549858 | L5: =D5*Premium!$C$23 -> 183.29915 | M5: =SUM(D5:E5)-SUM(F5:K5) -> 468.19759 | N5: =IF(Inputs!$D$9>=Cashflow!B5,SUM(D5:E5)-SUM(F5:K5)+N4,0) -> 438.71247
B6: 3 | C6: =C5+1 -> 42 | D6: =IF(Inputs!$D$10>=Cashflow!B6,Premium!$C$28*Premium_Calculations!D5,0) -> 610.3776 | E6: =IF(Inputs!$D$9>=Cashflow!B6,(D6-I6+N5-K6-H6-J6)*Inputs!$D$12,0) -> 49.097427 | F6: =Table2[[#This Row],[Benefits]] -> 110.18471 | G6: 0 | H6: 0 | I6: =IF(Inputs!$D$10>=Cashflow!B6,Premium!$C$28*Inputs!$D$14*Premium_Calculations!D5,0) -> 36.622656 | J6: 0 | K6: =IF(Inputs!$D$10>=Cashflow!B6,Premium!$C$28*Inputs!$D$16*Premium_Calculations!D5,0) -> 30.51888 | L6: =D6*Premium!$C$23 -> 183.11328 | M6: =SUM(D6:E6)-SUM(F6:K6) -> 482.14878 | N6: =IF(Inputs!$D$9>=Cashflow!B6,SUM(D6:E6)-SUM(F6:K6)+N5,0) -> 920.86124
B7: 4 | C7: =C6+1 -> 43 | D7: =IF(Inputs!$D$10>=Cashflow!B7,Premium!$C$28*Premium_Calculations!D6,0) -> 609.70374 | E7: =IF(Inputs!$D$9>=Cashflow!B7,(D7-I7+N6-K7-H7-J7)*Inputs!$D$12,0) -> 73.174879 | F7: =Table2[[#This Row],[Benefits]] -> 120.43133 | G7: 0 | H7: 0 | I7: =IF(Inputs!$D$10>=Cashflow!B7,Premium!$C$28*Inputs!$D$14*Premium_Calculations!D6,0) -> 36.582225 | J7: 0 | K7: =IF(Inputs!$D$10>=Cashflow!B7,Premium!$C$28*Inputs!$D$16*Premium_Calculations!D6,0) -> 30.485187 | L7: =D7*Premium!$C$23 -> 182.91112 | M7: =SUM(D7:E7)-SUM(F7:K7) -> 495.37988 | N7: =IF(Inputs!$D$9>=Cashflow!B7,SUM(D7:E7)-SUM(F7:K7)+N6,0) -> 1416.2411
B8: 5 | C8: =C7+1 -> 44 | D8: =IF(Inputs!$D$10>=Cashflow!B8,Premium!$C$28*Premium_Calculations!D7,0) -> 608.96722 | E8: =IF(Inputs!$D$9>=Cashflow!B8,(D8-I8+N7-K8-H8-J8)*Inputs!$D$12,0) -> 97.911098 | F8: =Table2[[#This Row],[Benefits]] -> 132.1352 | G8: 0 | H8: 0 | I8: =IF(Inputs!$D$10>=Cashflow!B8,Premium!$C$28*Inputs!$D$14*Premium_Calculations!D7,0) -> 36.538033 | J8: 0 | K8: =IF(Inputs!$D$10>=Cashflow!B8,Premium!$C$28*Inputs!$D$16*Premium_Calculations!D7,0) -> 30.448361 | L8: =D8*Premium!$C$23 -> 182.69017 | M8: =SUM(D8:E8)-SUM(F8:K8) -> 507.75672 | N8: =IF(Inputs!$D$9>=Cashflow!B8,SUM(D8:E8)-SUM(F8:K8)+N7,0) -> 1923.9978
B9: 6 | C9: =C8+1 -> 45 | D9: =IF(Inputs!$D$10>=Cashflow!B9,Premium!$C$28*Premium_Calculations!D8,0) -> 608.15912 | E9: =IF(Inputs!$D$9>=Cashflow!B9,(D9-I9+N8-K9-H9-J9)*Inputs!$D$12,0) -> 123.26297 | F9: =Table2[[#This Row],[Benefits]] -> 145.68289 | G9: 0 | H9: 0 | I9: =IF(Inputs!$D$10>=Cashflow!B9,Premium!$C$28*Inputs!$D$14*Premium_Calculations!D8,0) -> 36.489547 | J9: 0 | K9: =IF(Inputs!$D$10>=Cashflow!B9,Premium!$C$28*Inputs!$D$16*Premium_Calculations!D8,0) -> 30.407956 | L9: =D9*Premium!$C$23 -> 182.44774 | M9: =SUM(D9:E9)-SUM(F9:K9) -> 518.84171 | N9: =IF(Inputs!$D$9>=Cashflow!B9,SUM(D9:E9)-SUM(F9:K9)+N8,0) -> 2442.8396
B10: 7 | C10: =C9+1 -> 46 | D10: =IF(Inputs!$D$10>=Cashflow!B10,Premium!$C$28*Premium_Calculations!D9,0) -> 607.26817 | E10: =IF(Inputs!$D$9>=Cashflow!B10,(D10-I10+N9-K10-H10-J10)*Inputs!$D$12,0) -> 149.16541 | F10: =Table2[[#This Row],[Benefits]] -> 161.05902 | G10: 0 | H10: 0 | I10: =IF(Inputs!$D$10>=Cashflow!B10,Premium!$C$28*Inputs!$D$14*Premium_Calculations!D9,0) -> 36.43609 | J10: 0 | K10: =IF(Inputs!$D$10>=Cashflow!B10,Premium!$C$28*Inputs!$D$16*Premium_Calculations!D9,0) -> 30.363409 | L10: =D10*Premium!$C$23 -> 182.18045 | M10: =SUM(D10:E10)-SUM(F10:K10) -> 528.57506 | N10: =IF(Inputs!$D$9>=Cashflow!B10,SUM(D10:E10)-SUM(F10:K10)+N9,0) -> 2971.4146
B11: 8 | C11: =C10+1 -> 47 | D11: =IF(Inputs!$D$10>=Cashflow!B11,Premium!$C$28*Premium_Calculations!D10,0) -> 606.28318 | E11: =IF(Inputs!$D$9>=Cashflow!B11,(D11-I11+N10-K11-H11-J11)*Inputs!$D$12,0) -> 175.55033 | F11: =Table2[[#This Row],[Benefits]] -> 178.64217 | G11: 0 | H11: 0 | I11: =IF(Inputs!$D$10>=Cashflow!B11,Premium!$C$28*Inputs!$D$14*Premium_Calculations!D10,0) -> 36.376991 | J11: 0 | K11: =IF(Inputs!$D$10>=Cashflow!B11,Premium!$C$28*Inputs!$D$16*Premium_Calculations!D10,0) -> 30.314159 | L11: =D11*Premium!$C$23 -> 181.88495 | M11: =SUM(D11:E11)-SUM(F11:K11) -> 536.50019 | N11: =IF(Inputs!$D$9>=Cashflow!B11,SUM(D11:E11)-SUM(F11:K11)+N10,0) -> 3507.9148
B12: 9 | C12: =C11+1 -> 48 | D12: =IF(Inputs!$D$10>=Cashflow!B12,Premium!$C$28*Premium_Calculations!D11,0) -> 605.19066 | E12: =IF(Inputs!$D$9>=Cashflow!B12,(D12-I12+N11-K12-H12-J12)*Inputs!$D$12,0) -> 202.32672 | F12: =Table2[[#This Row],[Benefits]] -> 198.70537 | G12: 0 | H12: 0 | I12: =IF(Inputs!$D$10>=Cashflow!B12,Premium!$C$28*Inputs!$D$14*Premium_Calculations!D11,0) -> 36.31144 | J12: 0 | K12: =IF(Inputs!$D$10>=Cashflow!B12,Premium!$C$28*Inputs!$D$16*Premium_Calculations!D11,0) -> 30.259533 | L12: =D12*Premium!$C$23 -> 181.5572 | M12: =SUM(D12:E12)-SUM(F12:K12) -> 542.24104 | N12: =IF(Inputs!$D$9>=Cashflow!B12,SUM(D12:E12)-SUM(F12:K12)+N11,0) -> 4050.1558
B13: 10 | C13: =C12+1 -> 49 | D13: =IF(Inputs!$D$10>=Cashflow!B13,Premium!$C$28*Premium_Calculations!D12,0) -> 603.97544 | E13: =IF(Inputs!$D$9>=Cashflow!B13,(D13-I13+N12-K13-H13-J13)*Inputs!$D$12,0) -> 229.3847 | F13: =Table2[[#This Row],[Benefits]] -> 221.31702 | G13: 0 | H13: 0 | I13: =IF(Inputs!$D$10>=Cashflow!B13,Premium!$C$28*Inputs!$D$14*Premium_Calculations!D12,0) -> 36.238526 | J13: 0 | K13: =IF(Inputs!$D$10>=Cashflow!B13,Premium!$C$28*Inputs!$D$16*Premium_Calculations!D12,0) -> 30.198772 | L13: =D13*Premium!$C$23 -> 181.19263 | M13: =SUM(D13:E13)-SUM(F13:K13) -> 545.60581 | N13: =IF(Inputs!$D$9>=Cashflow!B13,SUM(D13:E13)-SUM(F13:K13)+N12,0) -> 4595.7617
B14: 11 | C14: =C13+1 -> 50 | D14: =IF(Inputs!$D$10>=Cashflow!B14,Premium!$C$28*Premium_Calculations!D13,0) -> 602.62193 | E14: =IF(Inputs!$D$9>=Cashflow!B14,(D14-I14+N13-K14-H14-J14)*Inputs!$D$12,0) -> 256.60476 | F14: =Table2[[#This Row],[Benefits]] -> 247.13039 | G14: 0 | H14: 0 | I14: =IF(Inputs!$D$10>=Cashflow!B14,Premium!$C$28*Inputs!$D$14*Premium_Calculations!D13,0) -> 36.157316 | J14: 0 | K14: =IF(Inputs!$D$10>=Cashflow!B14,Premium!$C$28*Inputs!$D$16*Premium_Calculations!D13,0) -> 30.131096 | L14: =D14*Premium!$C$23 -> 180.78658 | M14: =SUM(D14:E14)-SUM(F14:K14) -> 545.80789 | N14: =IF(Inputs!$D$9>=Cashflow!B14,SUM(D14:E14)-SUM(F14:K14)+N13,0) -> 5141.5695
B15: 12 | C15: =C14+1 -> 51 | D15: =IF(Inputs!$D$10>=Cashflow!B15,Premium!$C$28*Premium_Calculations!D14,0) -> 601.11055 | E15: =IF(Inputs!$D$9>=Cashflow!B15,(D15-I15+N14-K15-H15-J15)*Inputs!$D$12,0) -> 283.8279 | F15: =Table2[[#This Row],[Benefits]] -> 276.09579 | G15: 0 | H15: 0 | I15: =IF(Inputs!$D$10>=Cashflow!B15,Premium!$C$28*Inputs!$D$14*Premium_Calculations!D14,0) -> 36.066633 | J15: 0 | K15: =IF(Inputs!$D$10>=Cashflow!B15,Premium!$C$28*Inputs!$D$16*Premium_Calculations!D14,0) -> 30.055528 | L15: =D15*Premium!$C$23 -> 180.33317 | M15: =SUM(D15:E15)-SUM(F15:K15) -> 542.7205 | N15: =IF(Inputs!$D$9>=Cashflow!B15,SUM(D15:E15)-SUM(F15:K15)+N14,0) -> 5684.29
B16: 13 | C16: =C15+1 -> 52 | D16: =IF(Inputs!$D$10>=Cashflow!B16,Premium!$C$28*Premium_Calculations!D15,0) -> 599.42203 | E16: =IF(Inputs!$D$9>=Cashflow!B16,(D16-I16+N15-K16-H16-J16)*Inputs!$D$12,0) -> 310.88878 | F16: =Table2[[#This Row],[Benefits]] -> 308.9389 | G16: 0 | H16: 0 | I16: =IF(Inputs!$D$10>=Cashflow!B16,Premium!$C$28*Inputs!$D$14*Premium_Calculations!D15,0) -> 35.965322 | J16: 0 | K16: =IF(Inputs!$D$10>=Cashflow!B16,Premium!$C$28*Inputs!$D$16*Premium_Calculations!D15,0) -> 29.971102 | L16: =D16*Premium!$C$23 -> 179.82661 | M16: =SUM(D16:E16)-SUM(F16:K16) -> 535.43549 | N16: =IF(Inputs!$D$9>=Cashflow!B16,SUM(D16:E16)-SUM(F16:K16)+N15,0) -> 6219.7255
... B85: 82 | C85: =C84+1 -> 121 | D85: =IF(Inputs!$D$10>=Cashflow!B85,Premium!$C$28*Premium_Calculations!D84,0) -> 0 | E85: =IF(Inputs!$D$9>=Cashflow!B85,(D85-I85+N84-K85-H85-J85)*Inputs!$D$12,0) -> 0 | F85: =Table2[[#This Row],[Benefits]] -> 0 | G85: 0 | H85: 0 | I85: =IF(Inputs!$D$10>=Cashflow!B85,Premium!$C$28*Inputs!$D$14*Premium_Calculations!D84,0) -> 0 | J85: 0 | K85: =IF(Inputs!$D$10>=Cashflow!B85,Premium!$C$28*Inputs!$D$16*Premium_Calculations!D84,0) -> 0 | L85: =D85*Premium!$C$23 -> 0 | M85: =SUM(D85:E85)-SUM(F85:K85) -> 0 | N85: =IF(Inputs!$D$9>=Cashflow!B85,SUM(D85:E85)-SUM(F85:K85)+N84,0) -> 0
B86: TOTAL | D86: =SUM(D4:D85) -> 12014.001 | E86: =SUM(E4:E85) -> 8075.7808 | F86: =SUM(F4:F85) -> 18285.101 | G86: =SUM(G4:G85) -> 0 | H86: =SUM(H4:H85) -> 183.47106 | I86: =SUM(I4:I85) -> 684.14583 | J86: =SUM(J4:J85) -> 366.94212 | K86: =SUM(K4:K85) -> 570.12153 | L86: =D86*Premium!$C$23 -> 3604.2002 | M86: =SUM(M4:M85) -> 6.8212103e-13 | N86: =SUM(N4:N85) -> 151306.3

Sheet Premium
B3: ACTUARIAL LIFE INSURANCE PRICING ENGINE
B4: Policy Information
B5: Policy Number | C5: =Inputs!$D$5 -> POL0001
B6: Customer Name | C6: =Inputs!$D$6 -> Amit Sharma
B7: Product | C7: =Inputs!$D$19 -> Term
B8: Age | C8: =Inputs!$D$7 -> 40
B9: Gender | C9: =Inputs!$D$8 -> Male
B10: Policy Term(Years) | C10: =Inputs!$D$9 -> 30
B11: Premium Term(Years) | C11: =Inputs!$D$10 -> 20
B12: Sum Assured | C12: =Inputs!$D$11 -> 100000
B13: Interest Rate | C13: =Inputs!$D$12 -> 0.05
B16: Pricing Results
B17: EPV of Benefits | C17: =Calculations!$I$86 -> 6540.2965
B18: Premium Annuity Factor | C18: =Premium_Calculations!F86 -> 12.903674
B19: Net Premium | C19: =$C$17/$C$18 -> 506.85539
B22: Commercial Pricing
B23: Initial Expenses | C23: =Inputs!D13 -> 0.3
B24: Renewal Expenses | C24: =Inputs!D14 -> 0.06
B25: Initial Commission | C25: =Inputs!D15 -> 0.6
B26: Renewal Commission | C26: =Inputs!D16 -> 0.05
B27: Profit Loading | C27: =Inputs!D17 -> 0
B28: Gross Premium | C28: =(Premium!C17 + SUM(Premium_Calculations!H86:L86)) / Premium!C18 -> 611.57019
B31: Model Status
B32: ✔ Inputs Valid
B33: ✔ Mortality Loaded
B34: ✔ Premium Calculated
B35: ✔ Validation Passed

Sheet Dashboard
B2: Life Insurance Pricing Engine
B3: Excel-Based Actuarial Pricing Model
B5: Policy Information | F5: Net Premium | I5: Gross Premium | L5: EVP Benefits | O5: Investment Income | R5: EPV Expenses
B6: Policy Number | D6: =Inputs!D5 -> POL0001 | F6: =Premium!C19 -> 506.85539 | I6: =Premium!C28 -> 611.57019 | L6: =Premium!C17 -> 6540.2965 | O6: =Cashflow!E86 -> 8075.7808 | R6: =Premium_Calculations!I86 -> 436.79592
B7: Customer Name | D7: =Inputs!D6 -> Amit Sharma
B8: Age | D8: =Inputs!D7 -> 40
B9: Gender | D9: =Inputs!D8 -> Male
B10: Policy Term (Years) | D10: =Inputs!D9 -> 30
B11: Premium Term(Years) | D11: =Inputs!D10 -> 20
B12: Sum Assured | D12: =Inputs!D11 -> 100000
B13: Interest Rate | D13: =Inputs!D12 -> 0.05
B14: Initial Expenses | D14: =Inputs!D13 -> 0.3
B15: Renewal Expenses | D15: =Inputs!D14 -> 0.06
B16: Initial Commission | D16: =Inputs!D15 -> 0.6
B17: Renewal Commission | D17: =Inputs!D16 -> 0.05
B18: Profit Loading | D18: =Inputs!D17 -> 0

Sheet Checks
B3: Validation | E3: Status
B4: Age between 18–70 | E4: =IF(AND(Inputs!D7>=18,Inputs!D7<=70),"PASS","FAIL") -> PASS
B5: Policy Term between 5–50 | E5: =IF(AND(Inputs!D9>=5,Inputs!D9<=40),"PASS","FAIL") -> PASS
B6: Premium Term ≤ Policy Term | E6: =IF(Inputs!D10<=Inputs!D9,"PASS","FAIL") -> PASS
B7: Age + Policy Term ≤ Maximum Mortality Age | E7: =IF(Inputs!D7+Inputs!D9<=100,"PASS","FAIL") -> PASS
B8: Net Premium > 0 | E8: =IF(Premium!C19>0,"PASS","FAIL") -> PASS
B9: Gross Premium > Net Premium | E9: =IF(Premium!C28>Premium!C19,"PASS","FAIL") -> PASS
B10: Sum Assured > 0 | E10: =IF(Inputs!D11>0,"PASS","FAIL") -> PASS
B11: Expense Loading Valid | E11: =IF(Premium!C24>=0,"PASS","FAIL") -> PASS
B12: Profit Loading Valid | E12: =IF(Premium!C27>=0,"PASS","FAIL") -> PASS
B13: EPV Benefits > 0 | E13: =IF(Premium!C17>0,"PASS","FAIL") -> PASS
B14: Premium Annuity Factor > 0 | E14: =IF(Premium!C18>0,"PASS","FAIL") -> PASS
B15: Overall Model Status | E15: =IF(COUNTIF(E4:E14,"FAIL")=0,"MODEL READY","MODEL ERROR") -> MODEL READY
